girg_sampling/__init__.py
girg_sampling/_libgirgs_wrapper.cpp
girg_sampling/_libgirgs_wrapper.so
girg_sampling/_libhypergirgs_wrapper.cpp
girg_sampling/_libhypergirgs_wrapper.so
girg_sampling/girgs.py
girg_sampling/hypergirgs.py
girg_sampling/libgirgs.so.1
girg_sampling/libhypergirgs.so.1
girg_sampling-0.3.0.dist-info/METADATA
girg_sampling-0.3.0.dist-info/WHEEL
girg_sampling-0.3.0.dist-info/RECORD
