Metadata-Version: 2.1
Name: girg-sampling
Version: 0.3.0
Summary: Efficient sampling of Geometric Inhomogeneous Random Graphs (GIRG). Wrapper for C++ libraries libgirg and libhypergirg.
Home-page: https://github.com/gavento/girg-sampling
Author: Tomas Gavenciak
Author-email: gavento@gmail.com
Requires-Python: >=3.8,<4
Classifier: Programming Language :: Python :: 3
Classifier: Programming Language :: Python :: 3.8
Classifier: Programming Language :: Python :: 3.9
Classifier: Programming Language :: Python :: 3.10
Classifier: Programming Language :: Python :: 3.11
Project-URL: Repository, https://github.com/gavento/girg-sampling
